README.rst
setup.cfg
setup.py
easyci/__init__.py
easyci/__init__.pyc
easyci/cli.py
easyci/cli.pyc
easyci/commands
easyci/exit_codes.py
easyci/history.py
easyci/hooks
easyci/locking.py
easyci/results.py
easyci/user_config.py
easyci/user_config.pyc
easyci/utils
easyci/vcs
easyci/version.py
easyci.egg-info/PKG-INFO
easyci.egg-info/SOURCES.txt
easyci.egg-info/dependency_links.txt
easyci.egg-info/entry_points.txt
easyci.egg-info/pbr.json
easyci.egg-info/requires.txt
easyci.egg-info/top_level.txt
easyci/commands/__init__.py
easyci/commands/__init__.pyc
easyci/commands/clear_history.py
easyci/commands/gc.py
easyci/commands/init.py
easyci/commands/init.pyc
easyci/commands/test.py
easyci/commands/test.pyc
easyci/commands/watch.py
easyci/file_system_events/__init__.py
easyci/file_system_events/tests_event_handler.py
easyci/file_system_events/vcs_event_handler.py
easyci/hooks/__init__.py
easyci/hooks/__init__.pyc
easyci/hooks/hooks_manager.py
easyci/hooks/hooks_manager.pyc
easyci/hooks/pre-commit
easyci/hooks/pre-push
easyci/utils/__init__.py
easyci/utils/__init__.pyc
easyci/utils/contextmanagers.py
easyci/utils/contextmanagers.pyc
easyci/utils/decorators.py
easyci/vcs/__init__.py
easyci/vcs/__init__.pyc
easyci/vcs/base.py
easyci/vcs/base.pyc
easyci/vcs/git.py
easyci/vcs/git.pyc