Metadata-Version: 1.1
Name: easyci
Version: 2.0.1
Summary: Local CI, for mortals.
Home-page: https://github.com/naphatkrit/easyci
Author: Naphat Sanguansin
Author-email: naphat.krit@gmail.com
License: UNKNOWN
Download-URL: https://github.com/naphatkrit/easyci/tarball/2.0.1
Keywords: continuous,integration,easy,ci,gating,tests,testing,test,git
Platform: UNKNOWN
